alphafetcher/__init__.py
alphafetcher/wrapper/__init__.py
alphafetcher/wrapper/wrapper_utils.py
AlphaFetcher-0.2.0.dist-info/LICENSE
AlphaFetcher-0.2.0.dist-info/METADATA
AlphaFetcher-0.2.0.dist-info/WHEEL
AlphaFetcher-0.2.0.dist-info/top_level.txt
AlphaFetcher-0.2.0.dist-info/RECORD
