Metadata-Version: 2.1
Name: AlphaFetcher
Version: 0.2.0
Summary: This package allows interface with the AlphaFold Protein Structure Database. This package allows the download of entries' metadata an AlphaFold files (e.g. mmCIF, PAE, PDB...)
Home-page: https://bitbucket.org/bio2byte/alphafetcher/
Author: Jose Gavalda-Garcia
Author-email: jose.gavalda.garcia@vub.be
Maintainer: Jose Gavalda-Garcia
Maintainer-email: jose.gavalda.garcia@vub.be
License: OSI Approved :: GNU General Public License v3 (GPLv3)
Classifier: Natural Language :: English
Classifier: Programming Language :: Python :: 3.6
Classifier: Programming Language :: Python :: 3.7
Classifier: Programming Language :: Python :: 3.8
Classifier: Programming Language :: Python :: 3.9
Classifier: Programming Language :: Python :: 3.10
Classifier: Programming Language :: Python :: 3.11
Classifier: Programming Language :: Python :: 3.12
Classifier: License :: OSI Approved :: GNU General Public License v3 (GPLv3)
Classifier: Operating System :: OS Independent
Classifier: Topic :: Scientific/Engineering :: Bio-Informatics
Classifier: Intended Audience :: Science/Research
Classifier: Intended Audience :: Education
Classifier: Development Status :: 5 - Production/Stable
Requires-Python: >=3.6, <3.13
License-File: LICENSE
Requires-Dist: requests
Requires-Dist: tqdm
